scraper_yt/CommentsScraperdistribution.py
scraper_yt/__init__.py
scraper_yt-0.1.0.dist-info/METADATA
scraper_yt-0.1.0.dist-info/RECORD
scraper_yt-0.1.0.dist-info/WHEEL
scraper_yt-0.1.0.dist-info/top_level.txt
