Metadata-Version: 2.1
Name: scraper-yt
Version: 0.1.0
Summary: A package to scrape comments from a YouTube video
Home-page: https://github.com/sthitaprajna-mishra/scraper_yt
Author: Sthitaprajna Mishra
Author-email: sthitaprajna360@gmail.com
License: UNKNOWN
Platform: UNKNOWN
Classifier: Programming Language :: Python :: 3
Classifier: License :: OSI Approved :: MIT License
Classifier: Operating System :: OS Independent
Requires-Python: >=3.6
